wi_fi_attack/GenCharlist.py
wi_fi_attack/Get_AP.py
wi_fi_attack/__init__.py
wi_fi_attack/animation.py
wi_fi_attack/mac_address_detector.py
wi_fi_attack/network_scanner.py
wi_fi_attack/wifi_cracker.py
wi_fi_attack-4.0.5.dist-info/licenses/LICENSE
wi_fi_attack-4.0.5.dist-info/METADATA
wi_fi_attack-4.0.5.dist-info/WHEEL
wi_fi_attack-4.0.5.dist-info/entry_points.txt
wi_fi_attack-4.0.5.dist-info/top_level.txt
wi_fi_attack-4.0.5.dist-info/RECORD
