Metadata-Version: 2.4
Name: Wi-Fi-Attack
Version: 4.0.5
Summary: Wi-Fi attack toolkit for penetration testing (educational use only)
Home-page: https://github.com/cyb2rS2c/Wi-Fi_ATTACK
Author: cyb2rS2c
License: MIT
Classifier: Programming Language :: Python :: 3
Classifier: License :: OSI Approved :: MIT License
Classifier: Operating System :: POSIX :: Linux
Classifier: Environment :: Console
Classifier: Intended Audience :: Developers
Classifier: Development Status :: 5 - Production/Stable
Requires-Python: >=3.6
License-File: LICENSE
Requires-Dist: colorama
Requires-Dist: termcolor
Requires-Dist: pyfiglet
Requires-Dist: tabulate
Dynamic: author
Dynamic: classifier
Dynamic: description
Dynamic: description-content-type
Dynamic: home-page
Dynamic: license
Dynamic: license-file
Dynamic: requires-dist
Dynamic: requires-python
Dynamic: summary
